pybolano/__init__.py
pybolano/core/Lindblad_ME.py
pybolano/core/__init__.py
pybolano/core/commutators.py
pybolano/core/normal_ordering.py
pybolano/utils/__init__.py
pybolano/utils/error_handling.py
pybolano/utils/expval.py
pybolano/utils/multiprocessing.py
pybolano/utils/operators.py
pybolano-1.0.1.dist-info/LICENSE
pybolano-1.0.1.dist-info/METADATA
pybolano-1.0.1.dist-info/WHEEL
pybolano-1.0.1.dist-info/top_level.txt
pybolano-1.0.1.dist-info/RECORD
