Metadata-Version: 2.1
Name: pybolano
Version: 1.0.1
Summary: Symbolic normal (Wick) ordering involving bosonic ladder operators.
Author-email: Hendry Minfui Lim <hendry01@ui.ac.id>
License: MIT License
Project-URL: Repository, https://github.com/hendry24/pyBoLaNO
Project-URL: Issues, https://github.com/hendry24/pyBoLaNO/issues
Project-URL: Tutorial, https://github.com/hendry24/pyBoLaNO/blob/main/tutorial.ipynb
Keywords: boson,bosonic,ladder,operator,normal ordering,Wick ordering,annihilation,creation,symbolic
Classifier: Development Status :: 5 - Production/Stable
Classifier: Intended Audience :: Science/Research
Classifier: License :: OSI Approved :: MIT License
Requires-Python: >=3.8
License-File: LICENSE
Requires-Dist: sympy>=1.13.3
